junkie_picasso/__init__.py
junkie_picasso/junkie_picasso.py
junkie_picasso-2024.8.6.dist-info/LICENSE
junkie_picasso-2024.8.6.dist-info/METADATA
junkie_picasso-2024.8.6.dist-info/WHEEL
junkie_picasso-2024.8.6.dist-info/top_level.txt
junkie_picasso-2024.8.6.dist-info/RECORD
