Metadata-Version: 2.1
Name: junkie_picasso
Version: 2024.8.6
Summary: junkie_picasso adds abstract functionality to the junkie JUpyter NotebooK Image Explorer
Author-email: Raymond Hawkins <raymond.hawkins@mail.utoronto.ca>
Project-URL: Homepage, https://bitbucket.org/raymond_hawkins_utor/junkie_picasso
Project-URL: Bug Tracker, https://bitbucket.org/raymond_hawkins_utor/junkie_picasso/src/master/issues
Classifier: Programming Language :: Python :: 3.10
Classifier: License :: OSI Approved :: GNU General Public License v3 (GPLv3)
Classifier: Operating System :: OS Independent
Requires-Python: >=3.10
License-File: LICENSE
Requires-Dist: numpy >=1.23
Requires-Dist: ipympl >=0.9
Requires-Dist: ipywidgets >=8.0
Requires-Dist: matplotlib >=3.7
Requires-Dist: scikit-image
